Metadata-Version: 2.4
Name: pinpointPy-canary
Version: 1.3.3.3
Home-page: https://github.com/pinpoint-apm/pinpoint-c-agent
Author: cd_pinpoint members
Author-email: dl_cd_pinpoint@navercorp.com
License: Apache License 2.0
License-File: LICENSE
License-File: NOTICE
Dynamic: author
Dynamic: author-email
Dynamic: description
Dynamic: description-content-type
Dynamic: home-page
Dynamic: license
Dynamic: license-file
